{"Query": "Play Bino", "Label": "MEDIA"}
{"Query": "What's the score of the Suns and bucks game", "Label": "SPORTS"}
{"Query": "Is cereal a soup", "Label": "WEB"}
{"Query": "Hey Siri what's the humidity percentage right now", "Label": "WEATHER"}
{"Query": "Find me webpage for Don Allen service Center", "Label": "WEB"}
{"Query": "What's this song", "Label": "MEDIA"}
{"Query": "Hey Siri please look at the story in Instagram", "Label": "APPS"}
{"Query": "Hey Siri what time is it", "Label": "CLOCK"}
{"Query": "Hey Siri how many home runs did Woody Harrelson for the Mets have", "Label": "WEB"}
{"Query": "Hey Siri open up Apple Music", "Label": "APPS"}
